{
	"id": "918e903f-6193-4c37-b4db-4e950c3abf58",
	"name": "ASK-QA",
	"values": [
		{
			"key": "baseURL",
			"value": "http://ask-qa.portnov.com/api/v1",
			"type": "default",
			"enabled": true
		},
		{
			"key": "tokenTeacher",
			"value": "eyJhbGciOiJIUzI1NiIsInR5cCI6IkpXVCJ9.eyJlbWFpbCI6Im5hemlrbmF6MzEyQGdtYWlsLmNvbSIsImlhdCI6MTY5OTQ4OTcyMywiZXhwIjoxNjk5NTc2MTIzfQ.kPIM4lYOsKIC0jniYnaLFwRVo0zcJWtV4TjMHo-DtTk\n",
			"type": "default",
			"enabled": true
		},
		{
			"key": "tokenStudent",
			"value": "eyJhbGciOiJIUzI1NiIsInR5cCI6IkpXVCJ9.eyJlbWFpbCI6InBsYXllcnByQGFsc29haS5vbmxpbmUiLCJpYXQiOjE3MDAwMDcxOTAsImV4cCI6MTcwMDA5MzU5MH0.fckjdpMvL3Xa99pniA10xJDr-xuIZ2f8dgmUlai41s8",
			"type": "default",
			"enabled": true
		},
		{
			"key": "studentID",
			"value": "",
			"type": "any",
			"enabled": true
		},
		{
			"key": "quizID",
			"value": "",
			"type": "any",
			"enabled": true
		},
		{
			"key": "assignmentId",
			"value": "",
			"type": "any",
			"enabled": true
		},
		{
			"key": "assignmentGroupID",
			"value": "",
			"type": "any",
			"enabled": true
		},
		{
			"key": "activationCode",
			"value": "",
			"type": "any",
			"enabled": true
		},
		{
			"key": "studentEmail",
			"value": "graham12@deshivideos.com",
			"type": "default",
			"enabled": true
		}
	],
	"_postman_variable_scope": "environment",
	"_postman_exported_at": "2023-11-15T01:00:30.192Z",
	"_postman_exported_using": "Postman/10.19.17"
}